.gitignore
LICENSE.txt
Makefile
README.md
pre-commit.sh
pyproject.toml
minotaur/__init__.py
minotaur/__main__.py
minotaur/__version__.py
minotaur/_base.py
minotaur/_event.py
minotaur/_inotify.c
minotaur/_inotify.pyi
minotaur/_mask.py
minotaur/_minotaur.py
minotaur/py.typed
minotaur.egg-info/PKG-INFO
minotaur.egg-info/SOURCES.txt
minotaur.egg-info/dependency_links.txt
minotaur.egg-info/top_level.txt