Metadata-Version: 2.4
Name: minotaur
Version: 0.3.0
Summary: Pythonic, asynchronous, inotify interface.
Author-email: Gianni Tedesco <gianni@scaramanga.co.uk>
Maintainer-email: Gianni Tedesco <gianni@scaramanga.co.uk>
License: Apache 2.0
Project-URL: Homepage, https://github.com/giannitedesco/minotaur
Keywords: inotify,asynchronous,linux,file system
Platform: Linux
Classifier: Development Status :: 4 - Beta
Classifier: Intended Audience :: Developers
Classifier: Natural Language :: English
Classifier: Operating System :: POSIX :: Linux
Classifier: License :: OSI Approved :: Apache Software License
Classifier: Programming Language :: Python
Classifier: Programming Language :: Python :: 3
Classifier: Programming Language :: Python :: 3.9
Classifier: Programming Language :: Python :: Implementation :: CPython
Requires-Python: >=3.5
License-File: LICENSE.txt
Dynamic: license-file
